FLHT/__init__.py
FLHT-0.0.1.dist-info/LICENCE.txt
FLHT-0.0.1.dist-info/METADATA
FLHT-0.0.1.dist-info/WHEEL
FLHT-0.0.1.dist-info/top_level.txt
FLHT-0.0.1.dist-info/RECORD
